bridgeit/__init__.py
bridgeit/installers.py
bridgeit/magics.py
bridgeit/py.typed
bridgeit-0.1.3.dist-info/METADATA
bridgeit-0.1.3.dist-info/WHEEL
bridgeit-0.1.3.dist-info/licenses/LICENSE
bridgeit-0.1.3.dist-info/RECORD
