Metadata-Version: 2.4
Name: bridgeit
Version: 0.1.3
Summary: A modern Python library
Project-URL: Homepage, https://github.com/madhavajay/bridgeit
Project-URL: Repository, https://github.com/madhavajay/bridgeit
Project-URL: Issues, https://github.com/madhavajay/bridgeit/issues
Author-email: Madhava Jay <me@madhavajay.com>
License: Apache-2.0
License-File: LICENSE
Classifier: Development Status :: 3 - Alpha
Classifier: Intended Audience :: Developers
Classifier: License :: OSI Approved :: Apache Software License
Classifier: Programming Language :: Python :: 3
Classifier: Programming Language :: Python :: 3.12
Classifier: Programming Language :: Python :: 3.13
Classifier: Typing :: Typed
Requires-Python: >=3.12
Provides-Extra: dev
Requires-Dist: mypy>=1.8.0; extra == 'dev'
Requires-Dist: pytest-cov>=4.1.0; extra == 'dev'
Requires-Dist: pytest>=8.0.0; extra == 'dev'
Requires-Dist: ruff>=0.3.0; extra == 'dev'
